Audio_SpectraCLI/__init__.py
Audio_SpectraCLI/main-old.py
Audio_SpectraCLI/main.py
Audio_SpectraCLI-4.1.0.dist-info/LICENSE
Audio_SpectraCLI-4.1.0.dist-info/METADATA
Audio_SpectraCLI-4.1.0.dist-info/WHEEL
Audio_SpectraCLI-4.1.0.dist-info/top_level.txt
Audio_SpectraCLI-4.1.0.dist-info/RECORD
